<?xml version="1.0" encoding="utf-8"?>
<!--This config file defines the location of the UpdateManager deploy server.           -->
<!-- The name attribute is the environment name; usually "LIVE", "QA" or "TRAIN"        -->
<!-- The host attribute is the host name of the UpdateManager deploy server             -->
<!-- The port attribute is the port number of the UpdateManager deploy server           -->
<!-- Other attributes:                                                                  -->
<!--  verbosity - controls user interaction with Update Manager UI                      -->
<!--  updateInterval - number of minutes between automatic check for updates processing -->
<!--  assemblyLoadInterval - number of minutes between times the process loads known    -->
<!--           application assemblies to keep the user environment in a warmed up state -->
<configuration>
 
  <item Stationcode="AN-NI-1" cityid="1" />
  <item Stationcode="AN-NO-2" cityid="2" />
  <item Stationcode="AN-SO-3" cityid="3" />
  <item Stationcode="AN-AN-4" cityid="4" />
  <item Stationcode="AN-CH-5" cityid="5" />
  <item Stationcode="AN-CU-6" cityid="6" />
  <item Stationcode="AN-EA-7" cityid="7" />
  <item Stationcode="AN-GU-8" cityid="8" />
  <item Stationcode="AN-KR-9" cityid="9" />
  <item Stationcode="AN-KU-10" cityid="10" />
  <item Stationcode="AN-NE-11" cityid="11" />
  <item Stationcode="AN-PR-12" cityid="12" />
  <item Stationcode="AN-SR-13" cityid="13" />
  <item Stationcode="AN-VI-14" cityid="14" />
  <item Stationcode="AN-VI-15" cityid="15" />
  <item Stationcode="AN-WE-16" cityid="16" />
  <item Stationcode="AR-AN-17" cityid="17" />
  <item Stationcode="AR-CH-18" cityid="18" />
  <item Stationcode="AR-DI-19" cityid="19" />
  <item Stationcode="AR-EA-20" cityid="20" />
  <item Stationcode="AR-EA-21" cityid="21" />
  <item Stationcode="AR-KU-22" cityid="22" />
  <item Stationcode="AR-LO-23" cityid="23" />
  <item Stationcode="AR-LO-24" cityid="24" />
  <item Stationcode="AR-LO-25" cityid="25" />
  <item Stationcode="AR-LO-26" cityid="26" />
  <item Stationcode="AR-PA-27" cityid="27" />
  <item Stationcode="AR-TA-28" cityid="28" />
  <item Stationcode="AR-TI-29" cityid="29" />
  <item Stationcode="AR-UP-30" cityid="30" />
  <item Stationcode="AR-UP-31" cityid="31" />
  <item Stationcode="AR-WE-32" cityid="32" />
  <item Stationcode="AR-WE-33" cityid="33" />
  <item Stationcode="AS-BA-34" cityid="34" />
  <item Stationcode="AS-BA-35" cityid="35" />
  <item Stationcode="AS-BO-36" cityid="36" />
  <item Stationcode="AS-CA-37" cityid="37" />
  <item Stationcode="AS-CH-38" cityid="38" />
  <item Stationcode="AS-DA-39" cityid="39" />
  <item Stationcode="AS-DH-40" cityid="40" />
  <item Stationcode="AS-DH-41" cityid="41" />
  <item Stationcode="AS-DI-42" cityid="42" />
  <item Stationcode="AS-DI-43" cityid="43" />
  <item Stationcode="AS-GO-44" cityid="44" />
  <item Stationcode="AS-GO-45" cityid="45" />
  <item Stationcode="AS-HA-46" cityid="46" />
  <item Stationcode="AS-JO-47" cityid="47" />
  <item Stationcode="AS-KA-48" cityid="48" />
  <item Stationcode="AS-KA-49" cityid="49" />
  <item Stationcode="AS-KA-50" cityid="50" />
  <item Stationcode="AS-KA-51" cityid="51" />
  <item Stationcode="AS-KO-52" cityid="52" />
  <item Stationcode="AS-LA-53" cityid="53" />
  <item Stationcode="AS-MO-54" cityid="54" />
  <item Stationcode="AS-NA-55" cityid="55" />
  <item Stationcode="AS-NA-56" cityid="56" />
  <item Stationcode="AS-SI-57" cityid="57" />
  <item Stationcode="AS-SO-58" cityid="58" />
  <item Stationcode="AS-TI-59" cityid="59" />
  <item Stationcode="AS-UD-60" cityid="60" />
  <item Stationcode="BI-AR-61" cityid="61" />
  <item Stationcode="BI-AR-62" cityid="62" />
  <item Stationcode="BI-AU-63" cityid="63" />
  <item Stationcode="BI-BA-64" cityid="64" />
  <item Stationcode="BI-BE-65" cityid="65" />
  <item Stationcode="BI-BH-66" cityid="66" />
  <item Stationcode="BI-BH-67" cityid="67" />
  <item Stationcode="BI-BU-68" cityid="68" />
  <item Stationcode="BI-DA-69" cityid="69" />
  <item Stationcode="BI-EA-70" cityid="70" />
  <item Stationcode="BI-GA-71" cityid="71" />
  <item Stationcode="BI-GO-72" cityid="72" />
  <item Stationcode="BI-JA-73" cityid="73" />
  <item Stationcode="BI-JE-74" cityid="74" />
  <item Stationcode="BI-KA-75" cityid="75" />
  <item Stationcode="BI-KA-76" cityid="76" />
  <item Stationcode="BI-KH-77" cityid="77" />
  <item Stationcode="BI-KI-78" cityid="78" />
  <item Stationcode="BI-LA-79" cityid="79" />
  <item Stationcode="BI-MA-80" cityid="80" />
  <item Stationcode="BI-MA-81" cityid="81" />
  <item Stationcode="BI-MU-82" cityid="82" />
  <item Stationcode="BI-MU-83" cityid="83" />
  <item Stationcode="BI-NA-84" cityid="84" />
  <item Stationcode="BI-NA-85" cityid="85" />
  <item Stationcode="BI-PA-86" cityid="86" />
  <item Stationcode="BI-PU-87" cityid="87" />
  <item Stationcode="BI-RO-88" cityid="88" />
  <item Stationcode="BI-SA-89" cityid="89" />
  <item Stationcode="BI-SA-90" cityid="90" />
  <item Stationcode="BI-SA-91" cityid="91" />
  <item Stationcode="BI-SH-92" cityid="92" />
  <item Stationcode="BI-SH-93" cityid="93" />
  <item Stationcode="BI-SI-94" cityid="94" />
  <item Stationcode="BI-SI-95" cityid="95" />
  <item Stationcode="BI-SU-96" cityid="96" />
  <item Stationcode="BI-VA-97" cityid="97" />
  <item Stationcode="BI-WE-98" cityid="98" />
  <item Stationcode="CH-CH-99" cityid="99" />
  <item Stationcode="CH-BA-100" cityid="100" />
  <item Stationcode="CH-BA-101" cityid="101" />
  <item Stationcode="CH-BA-102" cityid="102" />
  <item Stationcode="CH-BA-103" cityid="103" />
  <item Stationcode="CH-BE-104" cityid="104" />
  <item Stationcode="CH-BI-105" cityid="105" />
  <item Stationcode="CH-BI-106" cityid="106" />
  <item Stationcode="CH-DA-107" cityid="107" />
  <item Stationcode="CH-DH-108" cityid="108" />
  <item Stationcode="CH-DU-109" cityid="109" />
  <item Stationcode="CH-GA-110" cityid="110" />
  <item Stationcode="CH-JA-111" cityid="111" />
  <item Stationcode="CH-JA-112" cityid="112" />
  <item Stationcode="CH-KA-113" cityid="113" />
  <item Stationcode="CH-KA-114" cityid="114" />
  <item Stationcode="CH-KO-115" cityid="115" />
  <item Stationcode="CH-KO-116" cityid="116" />
  <item Stationcode="CH-KO-117" cityid="117" />
  <item Stationcode="CH-MA-118" cityid="118" />
  <item Stationcode="CH-MU-119" cityid="119" />
  <item Stationcode="CH-NA-120" cityid="120" />
  <item Stationcode="CH-RA-121" cityid="121" />
  <item Stationcode="CH-RA-122" cityid="122" />
  <item Stationcode="CH-RA-123" cityid="123" />
  <item Stationcode="CH-SU-124" cityid="124" />
  <item Stationcode="CH-SU-125" cityid="125" />
  <item Stationcode="CH-SU-126" cityid="126" />
  <item Stationcode="DA-DA-127" cityid="127" />
  <item Stationcode="DA-DA-128" cityid="128" />
  <item Stationcode="DA-DI-129" cityid="129" />
  <item Stationcode="DE-CE-130" cityid="130" />
  <item Stationcode="DE-EA-131" cityid="131" />
  <item Stationcode="DE-NE-132" cityid="132" />
  <item Stationcode="DE-NO-133" cityid="133" />
  <item Stationcode="DE-NO-134" cityid="134" />
  <item Stationcode="DE-NO-135" cityid="135" />
  <item Stationcode="DE-SO-136" cityid="136" />
  <item Stationcode="DE-SO-137" cityid="137" />
  <item Stationcode="DE-WE-138" cityid="138" />
  <item Stationcode="GO-NO-139" cityid="139" />
  <item Stationcode="GO-SO-140" cityid="140" />
  <item Stationcode="GU-AH-141" cityid="141" />
  <item Stationcode="GU-AM-142" cityid="142" />
  <item Stationcode="GU-AN-143" cityid="143" />
  <item Stationcode="GU-AR-144" cityid="144" />
  <item Stationcode="GU-BA-145" cityid="145" />
  <item Stationcode="GU-BH-146" cityid="146" />
  <item Stationcode="GU-BH-147" cityid="147" />
  <item Stationcode="GU-BO-148" cityid="148" />
  <item Stationcode="GU-CH-149" cityid="149" />
  <item Stationcode="GU-DA-150" cityid="150" />
  <item Stationcode="GU-DA-151" cityid="151" />
  <item Stationcode="GU-DE-152" cityid="152" />
  <item Stationcode="GU-GA-153" cityid="153" />
  <item Stationcode="GU-GI-154" cityid="154" />
  <item Stationcode="GU-JA-155" cityid="155" />
  <item Stationcode="GU-JU-156" cityid="156" />
  <item Stationcode="GU-KA-157" cityid="157" />
  <item Stationcode="GU-KH-158" cityid="158" />
  <item Stationcode="GU-MA-159" cityid="159" />
  <item Stationcode="GU-ME-160" cityid="160" />
  <item Stationcode="GU-MO-161" cityid="161" />
  <item Stationcode="GU-NA-162" cityid="162" />
  <item Stationcode="GU-NA-163" cityid="163" />
  <item Stationcode="GU-PA-164" cityid="164" />
  <item Stationcode="GU-PA-165" cityid="165" />
  <item Stationcode="GU-PO-166" cityid="166" />
  <item Stationcode="GU-RA-167" cityid="167" />
  <item Stationcode="GU-SA-168" cityid="168" />
  <item Stationcode="GU-SU-169" cityid="169" />
  <item Stationcode="GU-SU-170" cityid="170" />
  <item Stationcode="GU-TA-171" cityid="171" />
  <item Stationcode="GU-VA-172" cityid="172" />
  <item Stationcode="GU-VA-173" cityid="173" />
  <item Stationcode="HA-AM-174" cityid="174" />
  <item Stationcode="HA-BH-175" cityid="175" />
  <item Stationcode="HA-FA-176" cityid="176" />
  <item Stationcode="HA-FA-177" cityid="177" />
  <item Stationcode="HA-GU-178" cityid="178" />
  <item Stationcode="HA-HI-179" cityid="179" />
  <item Stationcode="HA-JH-180" cityid="180" />
  <item Stationcode="HA-JI-181" cityid="181" />
  <item Stationcode="HA-KA-182" cityid="182" />
  <item Stationcode="HA-KA-183" cityid="183" />
  <item Stationcode="HA-KU-184" cityid="184" />
  <item Stationcode="HA-MA-185" cityid="185" />
  <item Stationcode="HA-ME-186" cityid="186" />
  <item Stationcode="HA-PA-187" cityid="187" />
  <item Stationcode="HA-PA-188" cityid="188" />
  <item Stationcode="HA-PA-189" cityid="189" />
  <item Stationcode="HA-RE-190" cityid="190" />
  <item Stationcode="HA-RO-191" cityid="191" />
  <item Stationcode="HA-SI-192" cityid="192" />
  <item Stationcode="HA-SO-193" cityid="193" />
  <item Stationcode="HA-YA-194" cityid="194" />
  <item Stationcode="HI-BI-195" cityid="195" />
  <item Stationcode="HI-CH-196" cityid="196" />
  <item Stationcode="HI-HA-197" cityid="197" />
  <item Stationcode="HI-KA-198" cityid="198" />
  <item Stationcode="HI-KI-199" cityid="199" />
  <item Stationcode="HI-KU-200" cityid="200" />
  <item Stationcode="HI-LA-201" cityid="201" />
  <item Stationcode="HI-MA-202" cityid="202" />
  <item Stationcode="HI-SH-203" cityid="203" />
  <item Stationcode="HI-SI-204" cityid="204" />
  <item Stationcode="HI-SO-205" cityid="205" />
  <item Stationcode="HI-UN-206" cityid="206" />
  <item Stationcode="JA-AN-207" cityid="207" />
  <item Stationcode="JA-BA-208" cityid="208" />
  <item Stationcode="JA-BA-209" cityid="209" />
  <item Stationcode="JA-BU-210" cityid="210" />
  <item Stationcode="JA-DO-211" cityid="211" />
  <item Stationcode="JA-GA-212" cityid="212" />
  <item Stationcode="JA-JA-213" cityid="213" />
  <item Stationcode="JA-KA-214" cityid="214" />
  <item Stationcode="JA-KA-215" cityid="215" />
  <item Stationcode="JA-KI-216" cityid="216" />
  <item Stationcode="JA-KU-217" cityid="217" />
  <item Stationcode="JA-KU-218" cityid="218" />
  <item Stationcode="JA-LE-219" cityid="219" />
  <item Stationcode="JA-PO-220" cityid="220" />
  <item Stationcode="JA-PU-221" cityid="221" />
  <item Stationcode="JA-RA-222" cityid="222" />
  <item Stationcode="JA-RA-223" cityid="223" />
  <item Stationcode="JA-RE-224" cityid="224" />
  <item Stationcode="JA-SA-225" cityid="225" />
  <item Stationcode="JA-SH-226" cityid="226" />
  <item Stationcode="JA-SR-227" cityid="227" />
  <item Stationcode="JA-UD-228" cityid="228" />
  <item Stationcode="JH-BO-229" cityid="229" />
  <item Stationcode="JH-CH-230" cityid="230" />
  <item Stationcode="JH-DE-231" cityid="231" />
  <item Stationcode="JH-DH-232" cityid="232" />
  <item Stationcode="JH-DU-233" cityid="233" />
  <item Stationcode="JH-EA-234" cityid="234" />
  <item Stationcode="JH-GA-235" cityid="235" />
  <item Stationcode="JH-GI-236" cityid="236" />
  <item Stationcode="JH-GO-237" cityid="237" />
  <item Stationcode="JH-GU-238" cityid="238" />
  <item Stationcode="JH-HA-239" cityid="239" />
  <item Stationcode="JH-JA-240" cityid="240" />
  <item Stationcode="JH-KH-241" cityid="241" />
  <item Stationcode="JH-KO-242" cityid="242" />
  <item Stationcode="JH-LA-243" cityid="243" />
  <item Stationcode="JH-LO-244" cityid="244" />
  <item Stationcode="JH-PA-245" cityid="245" />
  <item Stationcode="JH-PA-246" cityid="246" />
  <item Stationcode="JH-RA-247" cityid="247" />
  <item Stationcode="JH-RA-248" cityid="248" />
  <item Stationcode="JH-SA-249" cityid="249" />
  <item Stationcode="JH-SE-250" cityid="250" />
  <item Stationcode="JH-SI-251" cityid="251" />
  <item Stationcode="JH-WE-252" cityid="252" />
  <item Stationcode="KA-BA-253" cityid="253" />
  <item Stationcode="KA-BA-254" cityid="254" />
  <item Stationcode="KA-BA-255" cityid="255" />
  <item Stationcode="KA-BE-256" cityid="256" />
  <item Stationcode="KA-BE-257" cityid="257" />
  <item Stationcode="KA-BI-258" cityid="258" />
  <item Stationcode="KA-BI-259" cityid="259" />
  <item Stationcode="KA-CH-260" cityid="260" />
  <item Stationcode="KA-CH-261" cityid="261" />
  <item Stationcode="KA-CH-262" cityid="262" />
  <item Stationcode="KA-CH-263" cityid="263" />
  <item Stationcode="KA-DA-264" cityid="264" />
  <item Stationcode="KA-DA-265" cityid="265" />
  <item Stationcode="KA-DH-266" cityid="266" />
  <item Stationcode="KA-GA-267" cityid="267" />
  <item Stationcode="KA-GU-268" cityid="268" />
  <item Stationcode="KA-HA-269" cityid="269" />
  <item Stationcode="KA-HA-270" cityid="270" />
  <item Stationcode="KA-KO-271" cityid="271" />
  <item Stationcode="KA-KO-272" cityid="272" />
  <item Stationcode="KA-KO-273" cityid="273" />
  <item Stationcode="KA-MA-274" cityid="274" />
  <item Stationcode="KA-MY-275" cityid="275" />
  <item Stationcode="KA-RA-276" cityid="276" />
  <item Stationcode="KA-RA-277" cityid="277" />
  <item Stationcode="KA-SH-278" cityid="278" />
  <item Stationcode="KA-TU-279" cityid="279" />
  <item Stationcode="KA-UD-280" cityid="280" />
  <item Stationcode="KA-UT-281" cityid="281" />
  <item Stationcode="KA-YA-282" cityid="282" />
  <item Stationcode="KE-AL-283" cityid="283" />
  <item Stationcode="KE-ER-284" cityid="284" />
  <item Stationcode="KE-ID-285" cityid="285" />
  <item Stationcode="KE-KA-286" cityid="286" />
  <item Stationcode="KE-KA-287" cityid="287" />
  <item Stationcode="KE-KO-288" cityid="288" />
  <item Stationcode="KE-KO-289" cityid="289" />
  <item Stationcode="KE-KO-290" cityid="290" />
  <item Stationcode="KE-MA-291" cityid="291" />
  <item Stationcode="KE-PA-292" cityid="292" />
  <item Stationcode="KE-PA-293" cityid="293" />
  <item Stationcode="KE-TH-294" cityid="294" />
  <item Stationcode="KE-TH-295" cityid="295" />
  <item Stationcode="KE-WA-296" cityid="296" />
  <item Stationcode="LA-LA-297" cityid="297" />
  <item Stationcode="MA-AL-298" cityid="298" />
  <item Stationcode="MA-AN-299" cityid="299" />
  <item Stationcode="MA-AS-300" cityid="300" />
  <item Stationcode="MA-BA-301" cityid="301" />
  <item Stationcode="MA-BA-302" cityid="302" />
  <item Stationcode="MA-BE-303" cityid="303" />
  <item Stationcode="MA-BH-304" cityid="304" />
  <item Stationcode="MA-BH-305" cityid="305" />
  <item Stationcode="MA-BU-306" cityid="306" />
  <item Stationcode="MA-CH-307" cityid="307" />
  <item Stationcode="MA-CH-308" cityid="308" />
  <item Stationcode="MA-DA-309" cityid="309" />
  <item Stationcode="MA-DA-310" cityid="310" />
  <item Stationcode="MA-DE-311" cityid="311" />
  <item Stationcode="MA-DH-312" cityid="312" />
  <item Stationcode="MA-DI-313" cityid="313" />
  <item Stationcode="MA-GU-314" cityid="314" />
  <item Stationcode="MA-GW-315" cityid="315" />
  <item Stationcode="MA-HA-316" cityid="316" />
  <item Stationcode="MA-HO-317" cityid="317" />
  <item Stationcode="MA-IN-318" cityid="318" />
  <item Stationcode="MA-JA-319" cityid="319" />
  <item Stationcode="MA-JH-320" cityid="320" />
  <item Stationcode="MA-KA-321" cityid="321" />
  <item Stationcode="MA-KH-322" cityid="322" />
  <item Stationcode="MA-KH-323" cityid="323" />
  <item Stationcode="MA-MA-324" cityid="324" />
  <item Stationcode="MA-MA-325" cityid="325" />
  <item Stationcode="MA-MO-326" cityid="326" />
  <item Stationcode="MA-NA-327" cityid="327" />
  <item Stationcode="MA-NE-328" cityid="328" />
  <item Stationcode="MA-PA-329" cityid="329" />
  <item Stationcode="MA-RA-330" cityid="330" />
  <item Stationcode="MA-RA-331" cityid="331" />
  <item Stationcode="MA-RA-332" cityid="332" />
  <item Stationcode="MA-RE-333" cityid="333" />
  <item Stationcode="MA-SA-334" cityid="334" />
  <item Stationcode="MA-SA-335" cityid="335" />
  <item Stationcode="MA-SE-336" cityid="336" />
  <item Stationcode="MA-SE-337" cityid="337" />
  <item Stationcode="MA-SH-338" cityid="338" />
  <item Stationcode="MA-SH-339" cityid="339" />
  <item Stationcode="MA-SH-340" cityid="340" />
  <item Stationcode="MA-SH-341" cityid="341" />
  <item Stationcode="MA-SI-342" cityid="342" />
  <item Stationcode="MA-SI-343" cityid="343" />
  <item Stationcode="MA-TI-344" cityid="344" />
  <item Stationcode="MA-UJ-345" cityid="345" />
  <item Stationcode="MA-VI-347" cityid="347" />
  <item Stationcode="MA-UM-346" cityid="346" />
  <item Stationcode="MA-AH-348" cityid="348" />
  <item Stationcode="MA-AK-349" cityid="349" />
  <item Stationcode="MA-AM-350" cityid="350" />
  <item Stationcode="MA-AU-351" cityid="351" />
  <item Stationcode="MA-BE-352" cityid="352" />
  <item Stationcode="MA-BH-353" cityid="353" />
  <item Stationcode="MA-BU-354" cityid="354" />
  <item Stationcode="MA-CH-355" cityid="355" />
  <item Stationcode="MA-DH-356" cityid="356" />
  <item Stationcode="MA-GA-357" cityid="357" />
  <item Stationcode="MA-GO-358" cityid="358" />
  <item Stationcode="MA-HI-359" cityid="359" />
  <item Stationcode="MA-JA-360" cityid="360" />
  <item Stationcode="MA-JA-361" cityid="361" />
  <item Stationcode="MA-KO-362" cityid="362" />
  <item Stationcode="MA-LA-363" cityid="363" />
  <item Stationcode="MA-MU-364" cityid="364" />
  <item Stationcode="MA-MU-365" cityid="365" />
  <item Stationcode="MA-NA-366" cityid="366" />
  <item Stationcode="MA-NA-367" cityid="367" />
  <item Stationcode="MA-NA-368" cityid="368" />
  <item Stationcode="MA-NA-369" cityid="369" />
  <item Stationcode="MA-OS-370" cityid="370" />
  <item Stationcode="MA-PA-371" cityid="371" />
  <item Stationcode="MA-PU-372" cityid="372" />
  <item Stationcode="MA-RA-373" cityid="373" />
  <item Stationcode="MA-RA-374" cityid="374" />
  <item Stationcode="MA-SA-375" cityid="375" />
  <item Stationcode="MA-SA-376" cityid="376" />
  <item Stationcode="MA-SI-377" cityid="377" />
  <item Stationcode="MA-SO-378" cityid="378" />
  <item Stationcode="MA-TH-379" cityid="379" />
  <item Stationcode="MA-WA-380" cityid="380" />
  <item Stationcode="MA-WA-381" cityid="381" />
  <item Stationcode="MA-YA-382" cityid="382" />
  <item Stationcode="MA-BI-383" cityid="383" />
  <item Stationcode="MA-CH-384" cityid="384" />
  <item Stationcode="MA-CH-385" cityid="385" />
  <item Stationcode="MA-IM-386" cityid="386" />
  <item Stationcode="MA-IM-387" cityid="387" />
  <item Stationcode="MA-TA-389" cityid="389" />
  <item Stationcode="MA-SE-388" cityid="388" />
  <item Stationcode="MA-TH-390" cityid="390" />
  <item Stationcode="MA-UK-391" cityid="391" />
  <item Stationcode="ME-EA-392" cityid="392" />
  <item Stationcode="ME-EA-393" cityid="393" />
  <item Stationcode="ME-NO-395" cityid="395" />
  <item Stationcode="ME-EA-394" cityid="394" />
  <item Stationcode="ME-RI-396" cityid="396" />
  <item Stationcode="ME-SO-399" cityid="399" />
  <item Stationcode="ME-SO-397" cityid="397" />
  <item Stationcode="ME-SO-398" cityid="398" />
  <item Stationcode="ME-WE-400" cityid="400" />
  <item Stationcode="ME-SO-399" cityid="399" />
  <item Stationcode="ME-WE-400" cityid="400" />
  <item Stationcode="ME-WE-401" cityid="401" />
  <item Stationcode="ME-WE-402" cityid="402" />
  <item Stationcode="MI-AI-403" cityid="403" />
  <item Stationcode="MI-CH-404" cityid="404" />
  <item Stationcode="MI-KO-405" cityid="405" />
  <item Stationcode="MI-LA-406" cityid="406" />
  <item Stationcode="MI-LU-407" cityid="407" />
  <item Stationcode="MI-MA-408" cityid="408" />
  <item Stationcode="MI-SA-409" cityid="409" />
  <item Stationcode="MI-SE-410" cityid="410" />
  <item Stationcode="NA-DI-411" cityid="411" />
  <item Stationcode="NA-KI-412" cityid="412" />
  <item Stationcode="NA-KO-413" cityid="413" />
  <item Stationcode="NA-LO-414" cityid="414" />
  <item Stationcode="NA-MO-415" cityid="415" />
  <item Stationcode="NA-MO-416" cityid="416" />
  <item Stationcode="NA-PE-417" cityid="417" />
  <item Stationcode="NA-PH-418" cityid="418" />
  <item Stationcode="NA-TU-419" cityid="419" />
  <item Stationcode="NA-WO-420" cityid="420" />
  <item Stationcode="NA-ZU-421" cityid="421" />
  <item Stationcode="OD-AN-422" cityid="422" />
  <item Stationcode="OD-BA-423" cityid="423" />
  <item Stationcode="OD-BA-424" cityid="424" />
  <item Stationcode="OD-BA-425" cityid="425" />
  <item Stationcode="OD-BH-426" cityid="426" />
  <item Stationcode="OD-BO-427" cityid="427" />
  <item Stationcode="OD-CU-428" cityid="428" />
  <item Stationcode="OD-DH-430" cityid="430" />
  <item Stationcode="OD-GA-431" cityid="431" />
  <item Stationcode="OD-GA-432" cityid="432" />
  <item Stationcode="OD-JA-433" cityid="433" />
  <item Stationcode="OD-JA-434" cityid="434" />
  <item Stationcode="OD-JH-435" cityid="435" />
  <item Stationcode="OD-KA-436" cityid="436" />
  <item Stationcode="OD-KA-437" cityid="437" />
  <item Stationcode="OD-KE-438" cityid="438" />
  <item Stationcode="OD-KE-439" cityid="439" />
  <item Stationcode="OD-KH-440" cityid="440" />
  <item Stationcode="OD-KO-441" cityid="441" />
  <item Stationcode="OD-MA-442" cityid="442" />
  <item Stationcode="OD-MA-443" cityid="443" />
  <item Stationcode="OD-NA-444" cityid="444" />
  <item Stationcode="OD-NA-445" cityid="445" />
  <item Stationcode="OD-NU-446" cityid="446" />
  <item Stationcode="OD-PU-447" cityid="447" />
  <item Stationcode="OD-RA-448" cityid="448" />
  <item Stationcode="OD-SA-449" cityid="449" />
  <item Stationcode="OD-SO-450" cityid="450" />
  <item Stationcode="OD-SU-451" cityid="451" />
  <item Stationcode="PU-KA-452" cityid="452" />
  <item Stationcode="PU-MA-453" cityid="453" />
  <item Stationcode="PU-PO-454" cityid="454" />
  <item Stationcode="PU-YA-455" cityid="455" />
  <item Stationcode="PU-AM-456" cityid="456" />
  <item Stationcode="PU-BA-457" cityid="457" />
  <item Stationcode="PU-BA-458" cityid="458" />
  <item Stationcode="PU-FA-459" cityid="459" />
  <item Stationcode="PU-FA-460" cityid="460" />
  <item Stationcode="PU-FA-461" cityid="461" />
  <item Stationcode="PU-FE-462" cityid="462" />
  <item Stationcode="PU-GU-463" cityid="463" />
  <item Stationcode="PU-HO-464" cityid="464" />
  <item Stationcode="PU-JA-465" cityid="465" />
  <item Stationcode="PU-KA-466" cityid="466" />
  <item Stationcode="PU-LU-467" cityid="467" />
  <item Stationcode="PU-MA-468" cityid="468" />
  <item Stationcode="PU-MO-469" cityid="469" />
  <item Stationcode="PU-MU-470" cityid="470" />
  <item Stationcode="PU-NA-471" cityid="471" />
  <item Stationcode="PU-PA-472" cityid="472" />
  <item Stationcode="PU-PA-473" cityid="473" />
  <item Stationcode="PU-RU-474" cityid="474" />
  <item Stationcode="PU-SA-475" cityid="475" />
  <item Stationcode="PU-SA-476" cityid="476" />
  <item Stationcode="RA-AJ-478" cityid="478" />
  <item Stationcode="RA-AL-479" cityid="479" />
  <item Stationcode="RA-BA-480" cityid="480" />
  <item Stationcode="RA-BA-481" cityid="481" />
  <item Stationcode="RA-BA-482" cityid="482" />
  <item Stationcode="RA-BH-483" cityid="483" />
  <item Stationcode="RA-BH-484" cityid="484" />
  <item Stationcode="RA-BI-485" cityid="485" />
  <item Stationcode="RA-BU-486" cityid="486" />
  <item Stationcode="RA-CH-487" cityid="487" />
  <item Stationcode="RA-CH-488" cityid="488" />
  <item Stationcode="RA-DA-489" cityid="489" />
  <item Stationcode="RA-DH-490" cityid="490" />
  <item Stationcode="RA-DU-491" cityid="491" />
  <item Stationcode="RA-HA-492" cityid="492" />
  <item Stationcode="RA-JA-493" cityid="493" />
  <item Stationcode="RA-JA-494" cityid="494" />
  <item Stationcode="RA-JA-495" cityid="495" />
  <item Stationcode="RA-JH-496" cityid="496" />
  <item Stationcode="RA-JH-497" cityid="497" />
  <item Stationcode="RA-JO-498" cityid="498" />
  <item Stationcode="RA-KA-499" cityid="499" />
  <item Stationcode="RA-KO-500" cityid="500" />
  <item Stationcode="RA-NA-501" cityid="501" />
  <item Stationcode="RA-PA-502" cityid="502" />
  <item Stationcode="RA-PR-503" cityid="503" />
  <item Stationcode="RA-RA-504" cityid="504" />
  <item Stationcode="RA-SA-505" cityid="505" />
  <item Stationcode="RA-SI-506" cityid="506" />
  <item Stationcode="RA-SI-507" cityid="507" />
  <item Stationcode="RA-SR-508" cityid="508" />
  <item Stationcode="RA-TO-509" cityid="509" />
  <item Stationcode="RA-UD-510" cityid="510" />
  <item Stationcode="SI-EA-511" cityid="511" />
  <item Stationcode="SI-NO-512" cityid="512" />
  <item Stationcode="SI-SO-513" cityid="513" />
  <item Stationcode="SI-WE-514" cityid="514" />
  <item Stationcode="TA-AR-515" cityid="515" />
  <item Stationcode="TA-CH-516" cityid="516" />
  <item Stationcode="TA-CO-517" cityid="517" />
  <item Stationcode="TA-CU-518" cityid="518" />
  <item Stationcode="TA-DH-519" cityid="519" />
  <item Stationcode="TA-DI-520" cityid="520" />
  <item Stationcode="TA-ER-521" cityid="521" />
  <item Stationcode="TA-KA-522" cityid="522" />
  <item Stationcode="TA-KA-523" cityid="523" />
  <item Stationcode="TA-KA-524" cityid="524" />
  <item Stationcode="TA-KR-525" cityid="525" />
  <item Stationcode="TA-MA-526" cityid="526" />
  <item Stationcode="TA-NA-527" cityid="527" />
  <item Stationcode="TA-NA-528" cityid="528" />
  <item Stationcode="TA-NI-529" cityid="529" />
  <item Stationcode="TA-PE-530" cityid="530" />
  <item Stationcode="TA-PU-531" cityid="531" />
  <item Stationcode="TA-RA-532" cityid="532" />
  <item Stationcode="TA-SA-533" cityid="533" />
  <item Stationcode="TA-SI-534" cityid="534" />
  <item Stationcode="TA-TH-535" cityid="535" />
  <item Stationcode="TA-TH-536" cityid="536" />
  <item Stationcode="TA-TH-537" cityid="537" />
  <item Stationcode="TA-TI-538" cityid="538" />
  <item Stationcode="TA-TI-539" cityid="539" />
  <item Stationcode="TA-TI-540" cityid="540" />
  <item Stationcode="TA-TI-541" cityid="541" />
  <item Stationcode="TA-TI-542" cityid="542" />
  <item Stationcode="TA-TI-543" cityid="543" />
  <item Stationcode="TA-VE-544" cityid="544" />
  <item Stationcode="TA-VI-545" cityid="545" />
  <item Stationcode="TA-VI-546" cityid="546" />
  <item Stationcode="TE-AD-547" cityid="547" />
  <item Stationcode="TE-HY-548" cityid="548" />
  <item Stationcode="TE-KA-549" cityid="549" />
  <item Stationcode="TE-KH-550" cityid="550" />
  <item Stationcode="TE-MA-551" cityid="551" />
  <item Stationcode="TE-ME-552" cityid="552" />
  <item Stationcode="TE-NA-553" cityid="553" />
  <item Stationcode="TE-NI-554" cityid="554" />
  <item Stationcode="TE-RA-555" cityid="555" />
  <item Stationcode="TE-WA-556" cityid="556" />
  <item Stationcode="TR-DH-557" cityid="557" />
  <item Stationcode="TR-GO-558" cityid="558" />
  <item Stationcode="TR-KH-559" cityid="559" />
  <item Stationcode="TR-NO-560" cityid="560" />
  <item Stationcode="TR-SE-561" cityid="561" />
  <item Stationcode="TR-SO-562" cityid="562" />
  <item Stationcode="TR-UN-563" cityid="563" />
  <item Stationcode="TR-WE-564" cityid="564" />
  <item Stationcode="UT-AG-565" cityid="565" />
  <item Stationcode="UT-AL-566" cityid="566" />
  <item Stationcode="UT-AL-567" cityid="567" />
  <item Stationcode="UT-AM-568" cityid="568" />
  <item Stationcode="UT-AU-569" cityid="569" />
  <item Stationcode="UT-AZ-570" cityid="570" />
  <item Stationcode="UT-BA-571" cityid="571" />
  <item Stationcode="UT-BA-572" cityid="572" />
  <item Stationcode="UT-BA-573" cityid="573" />
  <item Stationcode="UT-BA-574" cityid="574" />
  <item Stationcode="UT-BA-575" cityid="575" />
  <item Stationcode="UT-BA-576" cityid="576" />
  <item Stationcode="UT-BA-577" cityid="577" />
  <item Stationcode="UT-BA-578" cityid="578" />
  <item Stationcode="UT-BH-579" cityid="579" />
  <item Stationcode="UT-BI-580" cityid="580" />
  <item Stationcode="UT-BU-581" cityid="581" />
  <item Stationcode="UT-BU-582" cityid="582" />
  <item Stationcode="UT-CH-583" cityid="583" />
  <item Stationcode="UT-CH-584" cityid="584" />
  <item Stationcode="UT-CH-585" cityid="585" />
  <item Stationcode="UT-DE-586" cityid="586" />
  <item Stationcode="UT-ET-587" cityid="587" />
  <item Stationcode="UT-ET-588" cityid="588" />
  <item Stationcode="UT-FA-589" cityid="589" />
  <item Stationcode="UT-FA-590" cityid="590" />
  <item Stationcode="UT-FA-591" cityid="591" />
  <item Stationcode="UT-FI-592" cityid="592" />
  <item Stationcode="UT-GA-593" cityid="593" />
  <item Stationcode="UT-GH-594" cityid="594" />
  <item Stationcode="UT-GH-595" cityid="595" />
  <item Stationcode="UT-GO-596" cityid="596" />
  <item Stationcode="UT-GO-597" cityid="597" />
  <item Stationcode="UT-HA-598" cityid="598" />
  <item Stationcode="UT-HA-599" cityid="599" />
  <item Stationcode="UT-HA-600" cityid="600" />
  <item Stationcode="UT-JA-601" cityid="601" />
  <item Stationcode="UT-JA-602" cityid="602" />
  <item Stationcode="UT-JH-603" cityid="603" />
  <item Stationcode="UT-JY-604" cityid="604" />
  <item Stationcode="UT-KA-605" cityid="605" />
  <item Stationcode="UT-KA-606" cityid="606" />
  <item Stationcode="UT-KA-607" cityid="607" />
  <item Stationcode="UT-KA-608" cityid="608" />
  <item Stationcode="UT-KA-609" cityid="609" />
  <item Stationcode="UT-KU-610" cityid="610" />
  <item Stationcode="UT-LA-611" cityid="611" />
  <item Stationcode="UT-LA-612" cityid="612" />
  <item Stationcode="UT-LU-613" cityid="613" />
  <item Stationcode="UT-MA-614" cityid="614" />
  <item Stationcode="UT-MA-615" cityid="615" />
  <item Stationcode="UT-MA-616" cityid="616" />
  <item Stationcode="UT-MA-617" cityid="617" />
  <item Stationcode="UT-MA-618" cityid="618" />
  <item Stationcode="UT-ME-619" cityid="619" />
  <item Stationcode="UT-MI-620" cityid="620" />
  <item Stationcode="UT-MO-621" cityid="621" />
  <item Stationcode="UT-MU-622" cityid="622" />
  <item Stationcode="UT-PA-623" cityid="623" />
  <item Stationcode="UT-PI-624" cityid="624" />
  <item Stationcode="UT-PR-625" cityid="625" />
  <item Stationcode="UT-PR-626" cityid="626" />
  <item Stationcode="UT-RA-627" cityid="627" />
  <item Stationcode="UT-RA-628" cityid="628" />
  <item Stationcode="UT-SA-629" cityid="629" />
  <item Stationcode="UT-SA-630" cityid="630" />
  <item Stationcode="UT-SA-631" cityid="631" />
  <item Stationcode="UT-SH-632" cityid="632" />
  <item Stationcode="UT-SH-633" cityid="633" />
  <item Stationcode="UT-SI-634" cityid="634" />
  <item Stationcode="UT-SI-635" cityid="635" />
  <item Stationcode="UT-SO-636" cityid="636" />
  <item Stationcode="UT-SU-637" cityid="637" />
  <item Stationcode="UT-UN-638" cityid="638" />
  <item Stationcode="UT-VA-639" cityid="639" />
  <item Stationcode="UT-AL-640" cityid="640" />
  <item Stationcode="UT-BA-641" cityid="641" />
  <item Stationcode="UT-CH-642" cityid="642" />
  <item Stationcode="UT-CH-643" cityid="643" />
  <item Stationcode="UT-HA-645" cityid="645" />
  <item Stationcode="UT-PA-647" cityid="647" />
  <item Stationcode="UT-RU-649" cityid="649" />
  <item Stationcode="UT-UD-651" cityid="651" />
  <item Stationcode="UT-UT-652" cityid="652" />
  <item Stationcode="WE-BA-653" cityid="653" />
  <item Stationcode="WE-BI-654" cityid="654" />
  <item Stationcode="WE-BU-655" cityid="655" />
  <item Stationcode="WE-CO-656" cityid="656" />
  <item Stationcode="WE-DA-657" cityid="657" />
  <item Stationcode="WE-DA-658" cityid="658" />
  <item Stationcode="WE-HO-659" cityid="659" />
  <item Stationcode="WE-HO-660" cityid="660" />
  <item Stationcode="WE-JA-661" cityid="661" />
  <item Stationcode="WE-KO-662" cityid="662" />
  <item Stationcode="WE-MA-663" cityid="663" />
  <item Stationcode="WE-MU-664" cityid="664" />
  <item Stationcode="WE-NA-665" cityid="665" />
  <item Stationcode="WE-NO-666" cityid="666" />
  <item Stationcode="WE-PA-667" cityid="667" />
  <item Stationcode="WE-PU-668" cityid="668" />
  <item Stationcode="WE-PU-669" cityid="669" />
  <item Stationcode="WE-SO-670" cityid="670" />
  <item Stationcode="WE-UT-671" cityid="671" />
</configuration>